{
    "default": {
        "1": {
            "best_resolution": "720p",
            "description": "",
            "download_url": "https://ev-ph.ypncdn.com/videos/202004/19/305148311/720P_1500K_305148311.mp4?rate=350k&burst=1600k&validfrom=1587553700&validto=1587568100&ip=127.0.0.1&hash=yCCorCnpEHSREOEY3O%2BwwGqL7r4%3D",
            "downloaded_at": "2020-04-22 00:00:00+00:00",
            "duration": "08:53",
            "featured_at": "2020-04-22 00:00:00+00:00",
            "file_name": "15941312.mp4",
            "from_category": "Eleganxia",
            "from_category_url": "https://www.youporn.com/channel/3793/eleganxia/",
            "id": "15941312",
            "original_file_name": "720P_1500K_305148311.mp4",
            "rating_percent": 60,
            "resolution": 720,
            "tags": [
                "Blonde",
                "Blowjob",
                "MILF",
                "Romantic",
                "milf",
                "erotic",
                "sensual",
                "blonde",
                "blowjob",
                "lingerie",
                "glamour",
                "sucking cock",
                "female friendly",
                "romantic",
                "stroke",
                "cum in mouth"
            ],
            "title": "Blonde Beauty Is The Best Cocksucker",
            "uploaded_at": "2020-04-19 00:00:00+00:00",
            "video_page_url": "https://www.youporn.com/watch/15941312/blonde-beauty-is-the-best-cocksucker/",
            "views": 501
        },
        "2": {
            "best_resolution": "720p",
            "description": "You've never seen lesbian assplay like this, trust us! Our horny college girls put on an orgasmic assortment of ass rimming and anal probing that will make you explode in pure ecstasy!",
            "download_url": "https://ev.ypncdn.com/202004/21/15944454/720p_1500k_15944454/YouPorn_-_ass-loving-lesbian.mp4?rate=350k&burst=1600k&validfrom=1587553900&validto=1587568300&ip=127.0.0.1&hash=CTrfiPiu605hE23GvSiHO0jaL2I%3D",
            "downloaded_at": "2020-04-22 00:00:00+00:00",
            "duration": "12:22",
            "featured_at": "2020-04-22 00:00:00+00:00",
            "file_name": "15944454.mp4",
            "from_category": "Simply Anal",
            "from_category_url": "https://www.youporn.com/channel/882546045/simply-anal/",
            "id": "15944454",
            "original_file_name": "YouPorn_-_ass-loving-lesbian.mp4",
            "rating_percent": 60,
            "resolution": 720,
            "tags": [
                "Francesca Dicaprio",
                "Dildos/Toys",
                "Lesbian",
                "Rimming",
                "Teen",
                "lesbian",
                "rimming",
                "kissing",
                "close up",
                "ass to mouth",
                "anal fingering",
                "russian",
                "blonde",
                "teen",
                "hd porn",
                "gape",
                "dildo",
                "pawg"
            ],
            "title": "Ass Loving Lesbian",
            "uploaded_at": "2020-04-21 00:00:00+00:00",
            "video_page_url": "https://www.youporn.com/watch/15944454/ass-loving-lesbian/",
            "views": 647
        },
        "3": {
            "best_resolution": "1080p",
            "description": "Alyssa Lynn was alone and horny so she whipped out her trusty dildo and went down on her pussy like never before!",
            "download_url": "https://ev.ypncdn.com/202004/17/15938642/720p_1500k_15938642/YouPorn_-_pornstarplatinum-big-tits-milf-alyssa-lynn-fucks-dildo-solo.mp4?rate=350k&burst=1600k&validfrom=1587554200&validto=1587568600&ip=127.0.0.1&hash=YLyMrP0t5pAF3F3j8DlLJPzjOcM%3D",
            "downloaded_at": "2020-04-22 00:00:00+00:00",
            "duration": "09:15",
            "featured_at": "2020-04-22 00:00:00+00:00",
            "file_name": "15938642.mp4",
            "from_category": "Pornstar Platinum",
            "from_category_url": "https://www.youporn.com/channel/2985/pornstar-platinum/",
            "id": "15938642",
            "original_file_name": "YouPorn_-_pornstarplatinum-big-tits-milf-alyssa-lynn-fucks-dildo-solo.mp4",
            "rating_percent": 20,
            "resolution": 720,
            "tags": [
                "Alyssa Lynn",
                "Big Tits",
                "MILF",
                "Masturbation",
                "Solo girl",
                "pornstarplatinum",
                "pornstar",
                "milf",
                "solo",
                "masturbation",
                "latina",
                "toys",
                "dildo",
                "big tits",
                "big ass",
                "lingerie",
                "tattoo",
                "hd",
                "fingering",
                "shaved"
            ],
            "title": "PORNSTARPLATINUM Big Tits MILF Alyssa Lynn Fucks Dildo Solo",
            "uploaded_at": "2020-04-17 00:00:00+00:00",
            "video_page_url": "https://www.youporn.com/watch/15938642/pornstarplatinum-big-tits-milf-alyssa-lynn-fucks-dildo-solo/",
            "views": 414
        },
        "4": {
            "best_resolution": "720p",
            "description": "",
            "download_url": "https://ev-ph.ypncdn.com/videos/202004/19/305236241/720P_1500K_305236241.mp4?rate=350k&burst=1600k&validfrom=1587554500&validto=1587568900&ip=127.0.0.1&hash=Q30hhKuKoB%2BorAZmUGTuMWX5j1w%3D",
            "downloaded_at": "2020-04-22 00:00:00+00:00",
            "duration": "12:05",
            "featured_at": "2020-04-22 00:00:00+00:00",
            "file_name": "15941506.mp4",
            "from_category": "Creampie Cathy",
            "from_category_url": "https://www.youporn.com/channel/502/creampie-cathy/",
            "id": "15941506",
            "original_file_name": "720P_1500K_305236241.mp4",
            "rating_percent": 64,
            "resolution": 720,
            "tags": [
                "Niki Snow",
                "Blowjob",
                "Gangbang",
                "Mature",
                "Teen",
                "bbc",
                "big cock",
                "blonde",
                "creampiecathy",
                "cumshot",
                "homemade",
                "mature",
                "teen",
                "hairy pussy",
                "gangbang",
                "creampies",
                "cum play",
                "swallow"
            ],
            "title": "Gangbang Sluts Get Multiple Creampies",
            "uploaded_at": "2020-04-19 00:00:00+00:00",
            "video_page_url": "https://www.youporn.com/watch/15941506/gangbang-sluts-get-multiple-creampies/",
            "views": 8996
        },
        "5": {
            "best_resolution": "1080p",
            "description": "",
            "download_url": "https://ev-ph.ypncdn.com/videos/202004/19/305288841/720P_1500K_305288841.mp4?rate=350k&burst=1600k&validfrom=1587554800&validto=1587569200&ip=127.0.0.1&hash=tbaPX33dQE5egOORGlPQ8KgsudA%3D",
            "downloaded_at": "2020-04-22 00:00:00+00:00",
            "duration": "06:50",
            "featured_at": "2020-04-22 00:00:00+00:00",
            "file_name": "15941676.mp4",
            "from_category": "Finish Him",
            "from_category_url": "https://www.youporn.com/channel/882546951/finish-him/",
            "id": "15941676",
            "original_file_name": "720P_1500K_305288841.mp4",
            "rating_percent": 20,
            "resolution": 720,
            "tags": [
                "Big Tits",
                "Blowjob",
                "HD",
                "Handjob",
                "Public",
                "balcony",
                "big boobs",
                "cumshot",
                "finishhim",
                "handjob",
                "jerking",
                "outside",
                "public",
                "smoking",
                "tucker stevens",
                "tugjob"
            ],
            "title": "\"Let me See You SPURT!\"Balcony Rub n Tug",
            "uploaded_at": "2020-04-19 00:00:00+00:00",
            "video_page_url": "https://www.youporn.com/watch/15941676/let-me-see-you-spurtbalcony-rub-n-tug/",
            "views": 2149
        },
        "6": {
            "best_resolution": "1080p",
            "description": "",
            "download_url": "https://ev-ph.ypncdn.com/videos/202003/12/292351491/720P_1500K_292351491.mp4?rate=350k&burst=1600k&validfrom=1587555000&validto=1587569400&ip=127.0.0.1&hash=yW8D%2FXTuN0PmpEMyrMjCnVgJC7w%3D",
            "downloaded_at": "2020-04-22 00:00:00+00:00",
            "duration": "10:15",
            "featured_at": "2020-04-22 00:00:00+00:00",
            "file_name": "15942626.mp4",
            "from_category": "Babestation X",
            "from_category_url": "https://www.youporn.com/channel/882548214/babestation-x/",
            "id": "15942626",
            "original_file_name": "720P_1500K_292351491.mp4",
            "rating_percent": 20,
            "resolution": 720,
            "tags": [
                "Xena",
                "Blonde",
                "European",
                "MILF",
                "Straight Sex",
                "babestationx",
                "big ass",
                "big dick",
                "british",
                "deepthroat",
                "demetri",
                "teen",
                "xena wilkes",
                "blonde",
                "milf",
                "missionary",
                "doggy",
                "busty"
            ],
            "title": "Xena Wilkes British cock lover",
            "uploaded_at": "2020-04-20 00:00:00+00:00",
            "video_page_url": "https://www.youporn.com/watch/15942626/xena-wilkes-british-cock-lover/",
            "views": 862
        },
        "7": {
            "best_resolution": "720p",
            "description": "",
            "download_url": "https://ev-ph.ypncdn.com/videos/202004/20/305468811/720P_1500K_305468811.mp4?rate=350k&burst=1600k&validfrom=1587555300&validto=1587569700&ip=127.0.0.1&hash=U9fJiRkM9GNzZ%2FVttNixRCcIjLk%3D",
            "downloaded_at": "2020-04-22 00:00:00+00:00",
            "duration": "12:00",
            "featured_at": "2020-04-21 00:00:00+00:00",
            "file_name": "15942608.mp4",
            "from_category": "Sexy Momma",
            "from_category_url": "https://www.youporn.com/channel/882546351/sexy-momma/",
            "id": "15942608",
            "original_file_name": "720P_1500K_305468811.mp4",
            "rating_percent": 100,
            "resolution": 720,
            "tags": [
                "Eva Longoria",
                "Lesbian",
                "MILF",
                "Step Fantasy",
                "Teen",
                "fingering",
                "hd",
                "lesbian",
                "milf",
                "scissoring",
                "sexymomma",
                "stepdaughter",
                "stepmom",
                "taboo",
                "teen",
                "teenager",
                "young",
                "pussy licking",
                "pawg",
                "69"
            ],
            "title": "Sixtynining les stepmom",
            "uploaded_at": "2020-04-20 00:00:00+00:00",
            "video_page_url": "https://www.youporn.com/watch/15942608/sixtynining-les-stepmom/",
            "views": 2679
        },
        "8": {
            "best_resolution": "1080p",
            "description": "",
            "download_url": "https://ev-ph.ypncdn.com/videos/202004/16/304398131/720P_1500K_304398131.mp4?rate=350k&burst=1600k&validfrom=1587555500&validto=1587569900&ip=127.0.0.1&hash=lhilJb2iqdtItmB9sT%2Fe8spCje4%3D",
            "downloaded_at": "2020-04-22 00:00:00+00:00",
            "duration": "11:34",
            "featured_at": "2020-04-21 00:00:00+00:00",
            "file_name": "15941724.mp4",
            "from_category": "Burning Angel",
            "from_category_url": "https://www.youporn.com/channel/3308/burning-angel/",
            "id": "15941724",
            "original_file_name": "720P_1500K_304398131.mp4",
            "rating_percent": 100,
            "resolution": 720,
            "tags": [
                "Kyle Mason",
                "Aiden Ashley",
                "Big Dick",
                "Blonde",
                "Blowjob",
                "Fingering",
                "Masturbation",
                "Rough Sex",
                "Small Tits",
                "Straight Sex",
                "Teen",
                "big dick",
                "blowjob",
                "burningangel",
                "choking",
                "clit rubbing",
                "deepthroat",
                "fingering",
                "hair pulling",
                "hardcore",
                "lingerie",
                "pounded",
                "pussy rubbing",
                "rough",
                "small",
                "submission",
                "throating",
                "tiny tits",
                "tits"
            ],
            "title": "Rough Sex Submission To That Big Cock - BurningAngel",
            "uploaded_at": "2020-04-19 00:00:00+00:00",
            "video_page_url": "https://www.youporn.com/watch/15941724/rough-sex-submission-to-that-big-cock-burningangel/",
            "views": 3157
        },
        "9": {
            "best_resolution": "1080p",
            "description": "",
            "download_url": "https://ev-ph.ypncdn.com/videos/202004/20/305733751/720P_1500K_305733751.mp4?rate=350k&burst=1600k&validfrom=1587555900&validto=1587570300&ip=127.0.0.1&hash=n%2B25FNdcc%2Fhv0uXdHWN1CBi014g%3D",
            "downloaded_at": "2020-04-22 00:00:00+00:00",
            "duration": "12:20",
            "featured_at": "2020-04-21 00:00:00+00:00",
            "file_name": "15943820.mp4",
            "from_category": "Manuel Ferrara",
            "from_category_url": "https://www.youporn.com/channel/882547047/manuel-ferrara/",
            "id": "15943820",
            "original_file_name": "720P_1500K_305733751.mp4",
            "rating_percent": 100,
            "resolution": 720,
            "tags": [
                "Manuel Ferrara",
                "Bella Rolland",
                "Anal",
                "Big Butt",
                "Big Dick",
                "Blowjob",
                "Brunette",
                "Cumshots",
                "POV",
                "Pussy Licking",
                "Swallow",
                "ass fuck",
                "big cock",
                "big dick",
                "butt",
                "manuelferrara",
                "natural tits",
                "point of view",
                "swallow"
            ],
            "title": "Manuel Ferrara - Bella Rolland Takes Manuels Thick Cock Up Her Tight Ass",
            "uploaded_at": "2020-04-20 00:00:00+00:00",
            "video_page_url": "https://www.youporn.com/watch/15943820/manuel-ferrara-bella-rolland-takes-manuels-thick-cock-up-her-tight-ass/",
            "views": 2643
        },
        "10": {
            "best_resolution": "720p",
            "description": "",
            "download_url": "https://cv-ph.ypncdn.com/videos/202004/20/305521451/720P_1500K_305521451.mp4?a5dcae8e1adc0bdaed975f0b6afb5e053704efd0eae2353da9090df5419f39355b8b34adafbe2520e9f1b245c4e72affe464daf12bc31611becee77cd322f1b21ca1c0a7f0762b315ed5058749fa554f7a24109effc7a6062e417accda5373aa7d276c3505fde5a9a0b160ac896a59ec4a70c751daef57715a7c0fa66506a204c4a292aee4bdffbc86aa92bf0df1831490f21ed149",
            "downloaded_at": "2020-04-22 00:00:00+00:00",
            "duration": "07:59",
            "featured_at": "2020-04-21 00:00:00+00:00",
            "file_name": "15942818.mp4",
            "from_category": "Parody Bros",
            "from_category_url": "https://www.youporn.com/channel/2901/parody-bros/",
            "id": "15942818",
            "original_file_name": "720P_1500K_305521451.mp4",
            "rating_percent": 87,
            "resolution": 720,
            "tags": [
                "Amateur",
                "Big Dick",
                "Blonde",
                "Blowjob",
                "Funny",
                "MILF",
                "Mature",
                "Parody",
                "Straight Sex",
                "Teen",
                "Vintage",
                "big cock",
                "classics",
                "comedy",
                "funny",
                "milf",
                "old",
                "parody",
                "parodybros",
                "seventies",
                "sixties",
                "teen",
                "tv",
                "vintage"
            ],
            "title": "Black And White Interracial Sexaholic",
            "uploaded_at": "2020-04-20 00:00:00+00:00",
            "video_page_url": "https://www.youporn.com/watch/15942818/black-and-white-interracial-sexaholic/",
            "views": 1492
        },
        "11": {
            "best_resolution": "1080p",
            "description": "",
            "download_url": "https://ev-ph.ypncdn.com/videos/202004/19/305392941/720P_1500K_305392941.mp4?rate=350k&burst=1600k&validfrom=1587556400&validto=1587570800&ip=127.0.0.1&hash=yAE21AK1MDvaWzdY9zJK0qyCHaM%3D",
            "downloaded_at": "2020-04-22 00:00:00+00:00",
            "duration": "23:09",
            "featured_at": "2020-04-21 00:00:00+00:00",
            "file_name": "15942288.mp4",
            "from_category": "Nebraska Coeds",
            "from_category_url": "https://www.youporn.com/channel/1773/nebraska-coeds/",
            "id": "15942288",
            "original_file_name": "720P_1500K_305392941.mp4",
            "rating_percent": 100,
            "resolution": 720,
            "tags": [
                "Amateur",
                "College",
                "Public",
                "Reality",
                "Teen",
                "nebraska jim",
                "nebraskacoeds",
                "public",
                "real",
                "spring break",
                "teenager",
                "wet t shirt",
                "young",
                "group",
                "outdoors",
                "pawg",
                "fingering",
                "amateurs",
                "teens",
                "skin to win"
            ],
            "title": "spring break back yard best homemade skin to win wet tshirt contest",
            "uploaded_at": "2020-04-19 00:00:00+00:00",
            "video_page_url": "https://www.youporn.com/watch/15942288/spring-break-back-yard-best-homemade-skin-to-win-wet-tshirt-contest/",
            "views": 2644
        },
        "12": {
            "best_resolution": "720p",
            "description": "",
            "download_url": "https://ev-ph.ypncdn.com/videos/202004/20/305539161/720P_1500K_305539161.mp4?rate=350k&burst=1600k&validfrom=1587557600&validto=1587572000&ip=127.0.0.1&hash=7zvi94%2Ff2a6SPl%2BRGVd%2BabLbIm0%3D",
            "downloaded_at": "2020-04-22 00:00:00+00:00",
            "duration": "12:00",
            "featured_at": "2020-04-21 00:00:00+00:00",
            "file_name": "15942816.mp4",
            "from_category": "Pascals Subsluts",
            "from_category_url": "https://www.youporn.com/channel/882545171/pascals-subsluts/",
            "id": "15942816",
            "original_file_name": "720P_1500K_305539161.mp4",
            "rating_percent": 100,
            "resolution": 720,
            "tags": [
                "Pascal White",
                "Silvia Dellai",
                "Amateur",
                "Anal",
                "Big Butt",
                "Big Tits",
                "Blowjob",
                "Dildos/Toys",
                "Fetish",
                "HD",
                "Masturbation",
                "Reality",
                "Rough Sex",
                "Straight Sex",
                "adult toys",
                "amateur",
                "anal",
                "ass fuck",
                "bdsm",
                "deepthroat",
                "fetish",
                "hardcore",
                "hd",
                "kink",
                "masturbation",
                "pascalssubsluts",
                "reality",
                "submissive",
                "toy"
            ],
            "title": "Throated kinky submissive",
            "uploaded_at": "2020-04-20 00:00:00+00:00",
            "video_page_url": "https://www.youporn.com/watch/15942816/throated-kinky-submissive/",
            "views": 2157
        },
        "13": {
            "best_resolution": "720p",
            "description": "Czech sex-goddess Nicolette wants you to watch as she plays out her freaky fetish of soaking herself with her own golden pee juices! Join the kinky cutie as she mops up her pissy mess and then indulges herself pussy by probing it with a speculum and big black dildo!",
            "download_url": "https://ev.ypncdn.com/202004/20/15942934/720p_1500k_15942934/YouPorn_-_soaked-in-her-own-pissy-liquid.mp4?rate=350k&burst=1600k&validfrom=1587558000&validto=1587572400&ip=127.0.0.1&hash=BQyzrzY2k555hBum0gBJaPO03Eo%3D",
            "downloaded_at": "2020-04-22 00:00:00+00:00",
            "duration": "12:22",
            "featured_at": "2020-04-21 00:00:00+00:00",
            "file_name": "15942934.mp4",
            "from_category": "Wet and Pissy",
            "from_category_url": "https://www.youporn.com/channel/2534/wet-and-pissy/",
            "id": "15942934",
            "original_file_name": "YouPorn_-_soaked-in-her-own-pissy-liquid.mp4",
            "rating_percent": 100,
            "resolution": 720,
            "tags": [
                "Nicolette Noir",
                "Brunette",
                "European",
                "Fetish",
                "Masturbation",
                "Pissing",
                "Shaved",
                "Small Tits",
                "Solo girl",
                "masturbation",
                "fingering",
                "close up",
                "piss in mouth",
                "sucking clothes",
                "peeing",
                "extreme pissing",
                "pee play",
                "czech",
                "teen",
                "solo girl",
                "black dildo",
                "wetandpissy",
                "brunette",
                "small tits",
                "shaved",
                "pissing"
            ],
            "title": "Soaked In Her Own Pissy Liquid",
            "uploaded_at": "2020-04-20 00:00:00+00:00",
            "video_page_url": "https://www.youporn.com/watch/15942934/soaked-in-her-own-pissy-liquid/",
            "views": 1142
        },
        "14": {
            "best_resolution": "1080p",
            "description": "",
            "download_url": "https://ev-ph.ypncdn.com/videos/202004/20/305700991/720P_1500K_305700991.mp4?rate=350k&burst=1600k&validfrom=1587558200&validto=1587572600&ip=127.0.0.1&hash=N3CdoBpLlXDMU5Glm6zyEXxUKq4%3D",
            "downloaded_at": "2020-04-22 00:00:00+00:00",
            "duration": "08:44",
            "featured_at": "2020-04-21 00:00:00+00:00",
            "file_name": "15943758.mp4",
            "from_category": "Puba",
            "from_category_url": "https://www.youporn.com/channel/2044/puba/",
            "id": "15943758",
            "original_file_name": "720P_1500K_305700991.mp4",
            "rating_percent": 87,
            "resolution": 720,
            "tags": [
                "Shyla Stylez",
                "Alexis Amore",
                "Big Tits",
                "MILF",
                "Straight Sex",
                "Threesome",
                "big boobs",
                "big tits",
                "blonde",
                "pornstar",
                "puba",
                "shyla stylez",
                "ffm",
                "brunette",
                "milf",
                "doggy",
                "blowjob",
                "glasses"
            ],
            "title": "Busty Shyla Stylez and Alexis Enjoy Sex!",
            "uploaded_at": "2020-04-20 00:00:00+00:00",
            "video_page_url": "https://www.youporn.com/watch/15943758/busty-shyla-stylez-and-alexis-enjoy-sex/",
            "views": 2439
        },
        "15": {
            "best_resolution": "1080p",
            "description": "",
            "download_url": "https://ev-ph.ypncdn.com/videos/202004/19/305340421/720P_1500K_305340421.mp4?rate=350k&burst=1600k&validfrom=1587558400&validto=1587572800&ip=127.0.0.1&hash=ztJOclmeZz94TKdhqBJS%2BFFtOAA%3D",
            "downloaded_at": "2020-04-22 00:00:00+00:00",
            "duration": "11:26",
            "featured_at": "2020-04-21 00:00:00+00:00",
            "file_name": "15941856.mp4",
            "from_category": "Slim 4K",
            "from_category_url": "https://www.youporn.com/channel/882548328/slim-4k/",
            "id": "15941856",
            "original_file_name": "720P_1500K_305340421.mp4",
            "rating_percent": 80,
            "resolution": 720,
            "tags": [
                "Blonde",
                "Squirting",
                "Straight Sex",
                "Teen",
                "1080p hd porn",
                "blonde",
                "blowjob",
                "creampie",
                "hanna rey",
                "orgasm",
                "petite",
                "slim",
                "slim4k",
                "squirting",
                "teen",
                "teenager",
                "young",
                "fast fuck",
                "pink pussy"
            ],
            "title": "Slim4K - hot blonde teen pussy creampied and have squirt",
            "uploaded_at": "2020-04-19 00:00:00+00:00",
            "video_page_url": "https://www.youporn.com/watch/15941856/slim4k-hot-blonde-teen-pussy-creampied-and-have-squirt/",
            "views": 2230
        },
        "16": {
            "best_resolution": "1080p",
            "description": "",
            "download_url": "https://ev-ph.ypncdn.com/videos/202004/19/305237771/720P_1500K_305237771.mp4?rate=350k&burst=1600k&validfrom=1587558600&validto=1587573000&ip=127.0.0.1&hash=jipglvzaUJbzoiAebF5Wxyg0L5o%3D",
            "downloaded_at": "2020-04-22 00:00:00+00:00",
            "duration": "13:12",
            "featured_at": "2020-04-21 00:00:00+00:00",
            "file_name": "15941510.mp4",
            "from_category": "Lesbea",
            "from_category_url": "https://www.youporn.com/channel/2213/lesbea/",
            "id": "15941510",
            "original_file_name": "720P_1500K_305237771.mp4",
            "rating_percent": 91,
            "resolution": 720,
            "tags": [
                "Angel Emily",
                "Brunette",
                "Gonzo",
                "HD",
                "Lesbian",
                "Romantic",
                "Small Tits",
                "69",
                "athletic",
                "bald pussy",
                "euro",
                "gonzo",
                "high heels",
                "intimate",
                "lesbea",
                "lesbian sex",
                "petite",
                "reality",
                "romantic",
                "romantic sex",
                "shaved pussy",
                "teacher",
                "tiny tina",
                "pussy licking",
                "fingering",
                "lesbian"
            ],
            "title": "Lesbea Tiny Tina lesbian pussy licking with French tutor Angel Emily",
            "uploaded_at": "2020-04-19 00:00:00+00:00",
            "video_page_url": "https://www.youporn.com/watch/15941510/lesbea-tiny-tina-lesbian-pussy-licking-with-french-tutor-angel-emily/",
            "views": 4382
        },
        "17": {
            "best_resolution": "1080p",
            "description": "",
            "download_url": "https://cv-ph.ypncdn.com/videos/202004/17/304597001/720P_1500K_304597001.mp4?a5dcae8e1adc0bdaed975f0b6afb5e053704efd0eae2353da9090df5419f39355b8b34adafbe2520e9f1b142c4e72afea479394ac4b37101fc347a1a4db5ff13f2e2c40ba164ae0b0fa1cbad78050cfcb4304a1c60bfb8e2358d4b4293b716d7c4524a88d4558bdfbc6c336a77ec127437c4472f464c38374dea2c36d4a70d4e194d3d8c658cff7b6c26dacaa2f98c1548b9078279",
            "downloaded_at": "2020-04-22 00:00:00+00:00",
            "duration": "10:30",
            "featured_at": "2020-04-21 00:00:00+00:00",
            "file_name": "15938552.mp4",
            "from_category": "Tu Venganza",
            "from_category_url": "https://www.youporn.com/channel/882547553/tu-venganza/",
            "id": "15938552",
            "original_file_name": "720P_1500K_304597001.mp4",
            "rating_percent": 92,
            "resolution": 720,
            "tags": [
                "Big Butt",
                "Big Dick",
                "Blowjob",
                "Cumshots",
                "Latina",
                "Reality",
                "Straight Sex",
                "big booty latina",
                "big cock",
                "butt",
                "cheating girlfriend",
                "cock sucking",
                "hard fuck",
                "latin",
                "letsdoeit",
                "mamacitaz",
                "natural tits",
                "nurse",
                "pawg",
                "revenge fuck",
                "shaved pussy",
                "tu venganza",
                "tuvenganza"
            ],
            "title": "Tu Venganza - A Cure For The Corona Is Getting Fucked By A Latina MamacitaZ",
            "uploaded_at": "2020-04-17 00:00:00+00:00",
            "video_page_url": "https://www.youporn.com/watch/15938552/tu-venganza-a-cure-for-the-corona-is-getting-fucked-by-a-latina-mamacitaz/",
            "views": 9137
        },
        "18": {
            "best_resolution": "1080p",
            "description": "",
            "download_url": "https://ev-ph.ypncdn.com/videos/202004/21/305942981/720P_1500K_305942981.mp4?rate=350k&burst=1600k&validfrom=1587559400&validto=1587573800&ip=127.0.0.1&hash=ILA%2F9fYlLmmxB9P1wyqNmYPIz%2FQ%3D",
            "downloaded_at": "2020-04-22 00:00:00+00:00",
            "duration": "11:00",
            "featured_at": "2020-04-22 00:00:00+00:00",
            "file_name": "15945488.mp4",
            "from_category": "Lets Doe It",
            "from_category_url": "https://www.youporn.com/channel/882547513/lets-doe-it/",
            "id": "15945488",
            "original_file_name": "720P_1500K_305942981.mp4",
            "rating_percent": 20,
            "resolution": 720,
            "tags": [
                "Alex Black",
                "Nata Lee",
                "Big Butt",
                "Big Tits",
                "Brunette",
                "Lesbian",
                "MILF",
                "Massage",
                "Teen",
                "big boobs",
                "butt",
                "girl on girl",
                "huge tits",
                "lesbian massage",
                "lesbian seduction",
                "lets doe it",
                "letsdoeit",
                "masseuse",
                "mom",
                "oil massage",
                "pawg",
                "perfect ass",
                "perfect tits",
                "relaxxxed",
                "wet pussy"
            ],
            "title": "Relaxxxed - Perfect Booty Babe Gets A Hot Massage From Huge Breast Masseuse",
            "uploaded_at": "2020-04-21 00:00:00+00:00",
            "video_page_url": "https://www.youporn.com/watch/15945488/relaxxxed-perfect-booty-babe-gets-a-hot-massage-from-huge-breast-masseuse/",
            "views": 296
        },
        "19": {
            "best_resolution": "1080p",
            "description": "Hot babe sucks them all off until she's covered in cum",
            "download_url": "https://ev.ypncdn.com/201907/05/15427920/720p_1500k_15427920/YouPorn_-_hot-babe-sucks-them-all-off-until-she-s-covered-in-cum.mp4?rate=350k&burst=1600k&validfrom=1587559800&validto=1587574200&ip=127.0.0.1&hash=zx5Il17H4ZSBkpSSRkVhtMj9BEE%3D",
            "downloaded_at": "2020-04-22 00:00:00+00:00",
            "duration": "08:08",
            "featured_at": "2020-04-22 00:00:00+00:00",
            "file_name": "15427920.mp4",
            "from_category": "Teen Nippon",
            "from_category_url": "https://www.youporn.com/channel/882547681/teen-nippon/",
            "id": "15427920",
            "original_file_name": "YouPorn_-_hot-babe-sucks-them-all-off-until-she-s-covered-in-cum.mp4",
            "rating_percent": 20,
            "resolution": 720,
            "tags": [
                "Blowjob",
                "Gangbang",
                "Japanese",
                "Teen",
                "teen",
                "gangbang",
                "hd",
                "busty",
                "nippleplay",
                "blowjob",
                "petite",
                "facial",
                "oil",
                "grope",
                "handjob",
                "bathingsuit",
                "cfnm"
            ],
            "title": "Hot babe sucks them all off until she's covered in cum",
            "uploaded_at": "2019-07-05 00:00:00+00:00",
            "video_page_url": "https://www.youporn.com/watch/15427920/hot-babe-sucks-them-all-off-until-shes-covered-in-cum/",
            "views": 1865
        },
        "20": {
            "best_resolution": "1080p",
            "description": "",
            "download_url": "https://ev-ph.ypncdn.com/videos/202004/19/305383901/720P_1500K_305383901.mp4?rate=350k&burst=1600k&validfrom=1587559900&validto=1587574300&ip=127.0.0.1&hash=WJybjeJLAn%2BKytEPTb7qwZdKoBQ%3D",
            "downloaded_at": "2020-04-22 00:00:00+00:00",
            "duration": "07:59",
            "featured_at": "2020-04-22 00:00:00+00:00",
            "file_name": "15942238.mp4",
            "from_category": "Nebraska Coeds",
            "from_category_url": "https://www.youporn.com/channel/1773/nebraska-coeds/",
            "id": "15942238",
            "original_file_name": "720P_1500K_305383901.mp4",
            "rating_percent": 20,
            "resolution": 720,
            "tags": [
                "Amateur",
                "Casting",
                "College",
                "European",
                "HD",
                "Masturbation",
                "POV",
                "Reality",
                "Teen",
                "casting",
                "dildo",
                "european",
                "first time",
                "innocent",
                "iwantslices",
                "masturbate",
                "nebraska coeds",
                "nebraska jim",
                "nebraskacoeds",
                "nervous",
                "point of view",
                "real",
                "shy",
                "toys",
                "watch her story"
            ],
            "title": "teen ella first time ever using a huge dildo on hidden camera",
            "uploaded_at": "2020-04-19 00:00:00+00:00",
            "video_page_url": "https://www.youporn.com/watch/15942238/teen-ella-first-time-ever-using-a-huge-dildo-on-hidden-camera/",
            "views": 515
        },
        "21": {
            "best_resolution": "480p",
            "description": "",
            "download_url": "https://cv-ph.ypncdn.com/videos/202004/20/305602271/480P_600K_305602271.mp4?a5dcae8e1adc0bdaed975f0b6bfb5e05376a38e6fc98b58f9c6b5e31d41a31ca23aeb02c0cd05b5316d97d3d20c06416711c78a3ff5cffc45848519de88ecc1828d33b3e2aabdbef05c7681a04ce8f14dd92159b31160128ba1909a73d9ac4aedb4c72e78dfc5a4484a4637e829b871e33dc8b1fb0932a62708ee620f89f222e03da63c062a5fb537451bf9cbd15d097d9da9da4",
            "downloaded_at": "2020-04-22 00:00:00+00:00",
            "duration": "08:00",
            "featured_at": "2020-04-21 00:00:00+00:00",
            "file_name": "15943106.mp4",
            "from_category": "Sex From Russia",
            "from_category_url": "https://www.youporn.com/channel/2376/sex-from-russia/",
            "id": "15943106",
            "original_file_name": "480P_600K_305602271.mp4",
            "rating_percent": 100,
            "resolution": 480,
            "tags": [
                "Amateur",
                "Anal",
                "Blowjob",
                "European",
                "Straight Sex",
                "Teen",
                "amateur",
                "anal",
                "blonde",
                "european",
                "hard",
                "mom",
                "moscow",
                "mother",
                "natural",
                "old",
                "rough",
                "russia",
                "russian",
                "sexfromrussia",
                "teen"
            ],
            "title": "Bored Russian Lady Gets Screwed",
            "uploaded_at": "2020-04-20 00:00:00+00:00",
            "video_page_url": "https://www.youporn.com/watch/15943106/bored-russian-lady-gets-screwed/",
            "views": 1491
        },
        "22": {
            "best_resolution": "1080p",
            "description": "Asian housewife fucks deep creamy asshole",
            "download_url": "https://ev.ypncdn.com/202001/23/15811730/720p_1500k_15811730/YouPorn_-_asian-housewife-fucks-deep-creamy-asshole.mp4?rate=342k&burst=1600k&validfrom=1587560300&validto=1587574700&ip=127.0.0.1&hash=9YO3RKA5wwR5WC4HsC3l7SpYeKE%3D",
            "downloaded_at": "2020-04-22 00:00:00+00:00",
            "duration": "06:37",
            "featured_at": "2020-04-21 00:00:00+00:00",
            "file_name": "15811730.mp4",
            "from_category": "cremeuxnikki",
            "from_category_url": "https://www.youporn.com/uservids/15367696/cremeuxnikki/",
            "id": "15811730",
            "original_file_name": "YouPorn_-_asian-housewife-fucks-deep-creamy-asshole.mp4",
            "rating_percent": 90,
            "resolution": 720,
            "tags": [
                "Asian",
                "Brunette",
                "Dildos/Toys",
                "HD",
                "MILF",
                "Shaved",
                "Small Tits",
                "Solo girl",
                "Webcam",
                "asian",
                "creamy",
                "creamy ass",
                "creamy cunt",
                "creamy asshole",
                "ass play",
                "anal play",
                "dildo",
                "toy",
                "masturbation",
                "webcam",
                "milf",
                "brunette",
                "small tits",
                "shaved",
                "fingering"
            ],
            "title": "Asian housewife fucks deep creamy asshole",
            "uploaded_at": "2020-01-23 00:00:00+00:00",
            "video_page_url": "https://www.youporn.com/watch/15811730/asian-housewife-fucks-deep-creamy-asshole/",
            "views": 23926
        },
        "23": {
            "best_resolution": "1080p",
            "description": "",
            "download_url": "https://ev-ph.ypncdn.com/videos/201907/21/236712021/720P_1500K_236712021.mp4?rate=350k&burst=1600k&validfrom=1587560500&validto=1587574900&ip=127.0.0.1&hash=Z3tferJf%2FHurCPugQPLSoIIt%2B7E%3D",
            "downloaded_at": "2020-04-22 00:00:00+00:00",
            "duration": "20:26",
            "featured_at": "2020-04-21 00:00:00+00:00",
            "file_name": "15491284.mp4",
            "from_category": "madeincanarias",
            "from_category_url": "https://www.youporn.com/uservids/8340151/ph-madeincanarias/",
            "id": "15491284",
            "original_file_name": "720P_1500K_236712021.mp4",
            "rating_percent": 90,
            "resolution": 720,
            "tags": [
                "Madeincanarias",
                "Manu Swan",
                "Amateur",
                "Anal",
                "Big Butt",
                "Big Dick",
                "Big Tits",
                "POV",
                "Teen",
                "Verified Amateurs",
                "anal",
                "ass fuck",
                "big ass",
                "big boobs",
                "big tits",
                "blowjob",
                "doggy style",
                "facial",
                "made in canarias",
                "madeincanarias",
                "missionary",
                "point of view",
                "spanish",
                "teen",
                "teenager",
                "young"
            ],
            "title": "Spanish teen babe with big tits LOVES anal sex and gets a huge facial",
            "uploaded_at": "2019-08-01 00:00:00+00:00",
            "video_page_url": "https://www.youporn.com/watch/15491284/spanish-teen-babe-with-big-tits-loves-anal-sex-and-gets-a-huge-facial/",
            "views": 166441
        },
        "24": {
            "best_resolution": "1080p",
            "description": "",
            "download_url": "https://cv-ph.ypncdn.com/videos/202004/20/305691071/720P_1500K_305691071.mp4?a5dcae8e1adc0bdaed975f0b6afb5e053704efd0eae2353da9090df5419f39355b8b34adafbe2520e9f1b245c4e72affe76fdaf529c3161144eb5f32b741798dc11acf2913e6cce1b4aa12bdd216d0edf13d015aa992d5f89e9dacb9660131c7ed06b89c811df308325cdee4b517b4063c5fcd9a1dab7806fdf8aeef0b1e7b4fadee93a071962047a9672c3455a85f4fe7f1eb1ec1",
            "downloaded_at": "2020-04-22 00:00:00+00:00",
            "duration": "08:45",
            "featured_at": "2020-04-21 00:00:00+00:00",
            "file_name": "15943658.mp4",
            "from_category": "Puba",
            "from_category_url": "https://www.youporn.com/channel/2044/puba/",
            "id": "15943658",
            "original_file_name": "720P_1500K_305691071.mp4",
            "rating_percent": 90,
            "resolution": 720,
            "tags": [
                "Elsa Jean",
                "Holly Heart",
                "Lesbian",
                "MILF",
                "Pussy Licking",
                "Teen",
                "big boobs",
                "blonde",
                "elsa jean",
                "fake tits",
                "lesbian",
                "petite",
                "pornstar",
                "puba",
                "small tits",
                "teen",
                "lingerie",
                "pussy licking",
                "pawg",
                "stockings"
            ],
            "title": "Elsa receives a lesson from her tutor!",
            "uploaded_at": "2020-04-20 00:00:00+00:00",
            "video_page_url": "https://www.youporn.com/watch/15943658/elsa-receives-a-lesson-from-her-tutor/",
            "views": 4983
        },
        "25": {
            "best_resolution": "1080p",
            "description": "deepthroat training on big dick",
            "download_url": "https://ev.ypncdn.com/201911/10/15675092/720p_1500k_15675092/YouPorn_-_deepthroat-training.mp4?rate=350k&burst=1600k&validfrom=1587561700&validto=1587576100&ip=127.0.0.1&hash=oqx6okVCp37wZGPmWrDePGdEAmw%3D",
            "downloaded_at": "2020-04-22 00:00:00+00:00",
            "duration": "07:24",
            "featured_at": "2020-04-21 00:00:00+00:00",
            "file_name": "15675092.mp4",
            "from_category": "greenbay19911",
            "from_category_url": "https://www.youporn.com/uservids/14736518/greenbay19911/",
            "id": "15675092",
            "original_file_name": "YouPorn_-_deepthroat-training.mp4",
            "rating_percent": 90,
            "resolution": 720,
            "tags": [
                "Big Dick",
                "Blowjob",
                "Facial",
                "HD",
                "POV",
                "Rough Sex",
                "Straight Sex",
                "Swallow",
                "deepthroat",
                "gag",
                "sloppy",
                "blowjob",
                "spit",
                "big dick",
                "cumslut",
                "gagging",
                "throat fuck",
                "nut",
                "pov",
                "deepthroating"
            ],
            "title": "deepthroat training",
            "uploaded_at": "2019-11-10 00:00:00+00:00",
            "video_page_url": "https://www.youporn.com/watch/15675092/deepthroat-training/",
            "views": 18813
        },
        "26": {
            "best_resolution": "1080p",
            "description": "Sexy blonde teen slut fingering, fucking and and sucking her dildo while parents are downstairs",
            "download_url": "https://cv.ypncdn.com/201911/12/15681696/720p_1500k_15681696/YouPorn_-_sexy-big-boobed-blonde-slut-fingering-fucking-and-and-sucking-her-dildo.mp4?a5dcae8e1adc0bdaed975c0d61fb5e057a15d67622dd9142db1cd2b60c27e0a67e7e60ecabe52f5732aba08a39a3ad62ee9e9af659b9a496cf5d5a7f25fc5e419b5d7d7b94ab07dafffc8b794c49b5b3482ea6630161e4a2974f9b85adcd94fd0164c70d4c889c1a36bed41dffa236c20e739dacef5c293dfa711929d955362c2ab35442a7b2c7de865f12dd89556be3884e5160f4c4f918140aadd8df8ccd7c23868a76d329feb7b67d74d869ca701647d08f474b00ea4ead0a336403750d3b9f8a263a4fc36384d462233c54c964eadade6292aeade33b5f43d15f85bb",
            "downloaded_at": "2020-04-22 00:00:00+00:00",
            "duration": "08:02",
            "featured_at": "2020-04-21 00:00:00+00:00",
            "file_name": "15681696.mp4",
            "from_category": "ultrapornlist",
            "from_category_url": "https://www.youporn.com/uservids/14867622/ultrapornlist/",
            "id": "15681696",
            "original_file_name": "YouPorn_-_sexy-big-boobed-blonde-slut-fingering-fucking-and-and-sucking-her-dildo.mp4",
            "rating_percent": 90,
            "resolution": 720,
            "tags": [
                "HD",
                "Solo girl",
                "Webcam",
                "boobs",
                "dildo",
                "dildo fucking",
                "fingering",
                "solo girl",
                "masturbation",
                "sucking dildo",
                "masturbationdildo",
                "solo",
                "blonde",
                "big tits",
                "busty",
                "babe"
            ],
            "title": "Sexy big boobed blonde slut fingering, fucking and and sucking her dildo",
            "uploaded_at": "2019-11-12 00:00:00+00:00",
            "video_page_url": "https://www.youporn.com/watch/15681696/sexy-big-boobed-blonde-slut-fingering-fucking-and-and-sucking-her-dildo/",
            "views": 61868
        },
        "27": {
            "best_resolution": "720p",
            "description": "",
            "download_url": "https://ev-ph.ypncdn.com/videos/202004/20/305730241/720P_1500K_305730241.mp4?rate=350k&burst=1600k&validfrom=1587561900&validto=1587576300&ip=127.0.0.1&hash=03p3%2BOUWdJKyZaszjTCW0gpu1MU%3D",
            "downloaded_at": "2020-04-22 00:00:00+00:00",
            "duration": "10:24",
            "featured_at": "2020-04-21 00:00:00+00:00",
            "file_name": "15943814.mp4",
            "from_category": "Cum4K",
            "from_category_url": "https://www.youporn.com/channel/882547153/cum4k/",
            "id": "15943814",
            "original_file_name": "720P_1500K_305730241.mp4",
            "rating_percent": 89,
            "resolution": 720,
            "tags": [
                "Vina Sky",
                "Asian",
                "Big Dick",
                "Blowjob",
                "Creampie",
                "Small Tits",
                "Straight Sex",
                "4k",
                "asian",
                "big cock",
                "big dick",
                "blowjob",
                "creampie",
                "cum4k",
                "doggystyle",
                "hardcore",
                "oral sex",
                "petite",
                "reverse cowgirl",
                "sex",
                "small tits",
                "vina sky"
            ],
            "title": "CUM4K MULTIPLE Leaking Creampies Deep Inside Wet Asian Pussy",
            "uploaded_at": "2020-04-20 00:00:00+00:00",
            "video_page_url": "https://www.youporn.com/watch/15943814/cum4k-multiple-leaking-creampies-deep-inside-wet-asian-pussy/",
            "views": 8538
        },
        "28": {
            "best_resolution": "1080p",
            "description": "",
            "download_url": "https://ev-ph.ypncdn.com/videos/202004/20/305711971/720P_1500K_305711971.mp4?rate=350k&burst=1600k&validfrom=1587562200&validto=1587576600&ip=127.0.0.1&hash=mBbfO1WUiggOG04f5PzOXV2M5no%3D",
            "downloaded_at": "2020-04-22 00:00:00+00:00",
            "duration": "12:35",
            "featured_at": "2020-04-21 00:00:00+00:00",
            "file_name": "15943740.mp4",
            "from_category": "Jules Jordan",
            "from_category_url": "https://www.youporn.com/channel/882547271/jules-jordan/",
            "id": "15943740",
            "original_file_name": "720P_1500K_305711971.mp4",
            "rating_percent": 89,
            "resolution": 720,
            "tags": [
                "Manuel Ferrara",
                "Scarlit Scandal",
                "Big Dick",
                "Blowjob",
                "Ebony",
                "Straight Sex",
                "big cocks",
                "big dick",
                "deep throat",
                "ebony",
                "facial",
                "interracial",
                "julesjordan",
                "tattoo",
                "rimming",
                "blowjob",
                "teen",
                "petite",
                "young"
            ],
            "title": "Jules Jordan - Ebony Beauty Scarlit Scandal Begs For More Cock",
            "uploaded_at": "2020-04-20 00:00:00+00:00",
            "video_page_url": "https://www.youporn.com/watch/15943740/jules-jordan-ebony-beauty-scarlit-scandal-begs-for-more-cock/",
            "views": 12849
        },
        "29": {
            "best_resolution": "1080p",
            "description": "",
            "download_url": "https://cv-ph.ypncdn.com/videos/201905/17/224130501/720P_4000K_224130501.mp4?a5dcae8e1adc0bdaed975f0d67fb5e0527c20903c5bb57a6cad7e6cb50bc41fbb1152c24e90eee013a84c1b4c7daa9d921821ffc1de37df0f5cfe22b41eaaf27719418e77bf96697d4c0e5ee5b6246a6f4d256afc2c75a47fd183f966e6b0371d28b99f3fc8a2a6b9a975cd63fbed822f79e533590710095be45afa7",
            "downloaded_at": "2020-04-23 00:00:00+00:00",
            "duration": "20:08",
            "featured_at": "2019-07-15 00:00:00+00:00",
            "file_name": "15369703.mp4",
            "from_category": "alex_adams",
            "from_category_url": "https://www.youporn.com/uservids/8831627/ph-alex_adams/",
            "id": "15369703",
            "original_file_name": "720P_4000K_224130501.mp4",
            "rating_percent": 76,
            "resolution": 720,
            "tags": [
                "Big Butt",
                "Big Tits",
                "Blonde",
                "HD",
                "MILF",
                "Teen",
                "Verified Amateurs",
                "alex adams",
                "archie stone",
                "big boobs",
                "brianna beach",
                "butt",
                "cheating wife",
                "fake tits",
                "family therapy",
                "milf fucks young guy",
                "mom",
                "mom comes first",
                "mother",
                "step mom",
                "teenager",
                "young"
            ],
            "title": "Mother Welcomes Home Step Son - Brianna Beach",
            "uploaded_at": "2019-06-06 00:00:00+00:00",
            "video_page_url": "https://www.youporn.com/watch/15369703/mother-welcomes-home-step-son-brianna-beach/",
            "views": 13598068
        }
    }
}